xj_tools/__init__.py
xj_tools/custom_authorization.py
xj_tools/custom_response.py
xj_tools/model_handle.py
xj_tools/validator.py
xj_tools-1.0.0.dist-info/METADATA
xj_tools-1.0.0.dist-info/WHEEL
xj_tools-1.0.0.dist-info/top_level.txt
xj_tools-1.0.0.dist-info/RECORD
