Metadata-Version: 2.1
Name: xj-tools
Version: 1.0.0
Summary: 工具类
Home-page: UNKNOWN
License: apache 3.0
Platform: UNKNOWN
Requires-Dist: django (==3.2.5)
Requires-Dist: djangorestframework
Requires-Dist: xj-user
